{"commitInfo":{"timestamp":1777052728690,"operation":"DELETE","operationParameters":{"predicate":"[\"(palavra#2568 = Engenharia)\"]"},"readVersion":2,"isolationLevel":"Serializable","isBlindAppend":false,"operationMetrics":{"numRemovedFiles":"1","numRemovedBytes":"747","numCopiedRows":"0","numDeletionVectorsAdded":"0","numDeletionVectorsRemoved":"0","numAddedChangeFiles":"0","executionTimeMs":"914","numDeletionVectorsUpdated":"0","numDeletedRows":"1","scanTimeMs":"751","numAddedFiles":"0","numAddedBytes":"0","rewriteTimeMs":"162"},"engineInfo":"Apache-Spark/3.5.0 Delta-Lake/3.0.0","txnId":"22ba60c6-0c02-4336-b6e1-ba13bd67f6e7"}}
{"remove":{"path":"part-00000-d4bcf88e-f03a-4403-9908-e904346f81b4-c000.snappy.parquet","deletionTimestamp":1777052728676,"dataChange":true,"extendedFileMetadata":true,"partitionValues":{},"size":747}}
